{
  "notes": [
    {
      "id": "1",
      "content": "HTML is easy",
      "important": true
    },
    {
      "id": "2",
      "content": "Browser can execute only JavaScript",
      "important": false
    },
    {
      "id": "3",
      "content": "GET and POST are the most important methods of HTTP protocol",
      "important": false
    },
    {
      "id": "9cfe",
      "content": "a new note...",
      "important": true
    },
    {
      "id": "d9e7",
      "content": "",
      "important": false
    },
    {
      "id": "6b8b",
      "content": "a new note...",
      "important": true
    },
    {
      "id": "e578",
      "content": "a new note...fasda",
      "important": true
    },
    {
      "id": "b193",
      "content": "a new note...",
      "important": false
    }
  ]
}